paips/__init__.py
paips/core.py
paips/run_paips.py
paips/utils/__init__.py
paips/utils/cache.py
paips/utils/config_processors.py
paips/utils/diagnose.py
paips/utils/file.py
paips/utils/graphs.py
paips/utils/logger.py
paips/utils/modiuls.py
paips/utils/nested.py
paips/utils/settings.py
paips-0.0.4.dist-info/METADATA
paips-0.0.4.dist-info/WHEEL
paips-0.0.4.dist-info/entry_points.txt
paips-0.0.4.dist-info/top_level.txt
paips-0.0.4.dist-info/RECORD
