Metadata-Version: 2.1
Name: paips
Version: 0.0.4
Summary: Run complex pipelines from terminal using configuration files
Home-page: https://github.com/mrpep/paips
Author: Leonardo Pepino
Author-email: leonardodpepino@gmail.com
License: UNKNOWN
Platform: UNKNOWN
Classifier: Programming Language :: Python :: 3
Classifier: Operating System :: OS Independent
Requires-Python: >=3.6
Requires-Dist: pyknife (>=0.0.3)
Requires-Dist: kahnfigh (>=0.0.2)
Requires-Dist: networkx (>=2.5.1)
Requires-Dist: joblib (>=1.0.1)
